[
    {
        "text":"It is a long established fact that a reader will be distracted by the readable content of a page when looking at its layout. The point of using Lorem Ipsum is that it has a more-or-less normal distribution of letters,",
        "category":"peach",
        "points":200
    },
    {
        "text":"It is a long established fact that a reader will be distracted by the readable content of a page when looking at its layout. The point of using Lorem Ipsum is that it has a more-or-less normal distribution of letters,",
        "category":"Hi",
        "points":987
    },
    {
        "text":"Fight",
        "category":"cognitive",
        "points":321
    }
]